packly/pk.py
packly-0.1.1.dist-info/METADATA
packly-0.1.1.dist-info/WHEEL
packly-0.1.1.dist-info/entry_points.txt
packly-0.1.1.dist-info/RECORD
