Metadata-Version: 2.1
Name: packly
Version: 0.1.1
Summary: Packly makes Python packaging easy
Author: dylanopen
Author-email: opendylan@proton.me
Requires-Python: >=3.11,<4.0
Classifier: Programming Language :: Python :: 3
Classifier: Programming Language :: Python :: 3.11
